combine_harvester.py
utils.py
combine_harvester-0.3.2.dist-info/entry_points.txt
combine_harvester-0.3.2.dist-info/LICENSE
combine_harvester-0.3.2.dist-info/WHEEL
combine_harvester-0.3.2.dist-info/METADATA
combine_harvester-0.3.2.dist-info/RECORD
