Metadata-Version: 2.1
Name: combine-harvester
Version: 0.3.2
Summary: CLI tool to log Harvest timesheets with FZF 
Home-page: https://github.com/BamBalaam/combine-harvester
License: GPL-3.0
Keywords: fzf,harvest,harvest-api,time-tracker,time-tracking
Author: André Madeira Cortes
Author-email: amadeiracortes@gmail.com
Requires-Python: >=3.6,<4.0
Classifier: Development Status :: 4 - Beta
Classifier: Environment :: Console
Classifier: License :: OSI Approved :: GNU General Public License v3 (GPLv3)
Classifier: Programming Language :: Python :: 3
Classifier: Programming Language :: Python :: 3.6
Classifier: Programming Language :: Python :: 3.7
Classifier: Programming Language :: Python :: 3.8
Requires-Dist: click (>=7.1.2,<8.0.0)
Requires-Dist: iso8601 (>=0.1.12,<0.2.0)
Requires-Dist: pyfzf (>=0.2.1,<0.3.0)
Requires-Dist: requests (>=2.23.0,<3.0.0)
Project-URL: Repository, https://github.com/BamBalaam/combine-harvester
